kstpy/__init__.py
kstpy/basics.py
kstpy/data.py
kstpy/graphics.py
kstpy/helpers.py
kstpy/io.py
kstpy/simulation.py
kstpy/validation.py
kstpy-1.0.0.dist-info/LICENSE
kstpy-1.0.0.dist-info/METADATA
kstpy-1.0.0.dist-info/WHEEL
kstpy-1.0.0.dist-info/RECORD
