Metadata-Version: 2.3
Name: kstpy
Version: 1.0.0
Summary: A Python package for Knowledge Space Theory
License: LGPL-3.0-or-later
Keywords: Knowledge Space Theory,Knowledge Structures,Psychology
Author: Cord Hockemeyer
Author-email: cord.hockemeyer@uni-graz.at
Requires-Python: >=3.11,<4.0
Classifier: Development Status :: 4 - Beta
Classifier: Topic :: Software Development :: Libraries :: Python Modules
Requires-Dist: matplotlib (>=3.10,<4.0)
Requires-Dist: more_itertools (>=10.6,<11.0)
Requires-Dist: networkx (>=3.4,<4.0)
Requires-Dist: numpy (>=2.2,<3.0)
Project-URL: Documentation, https://resources.cord-hockemeyer.info/techreports/kstpy.pdf
Project-URL: Homepage, https://www.cord-hockemeyer.info/en/knowledge-space-theory/resources-on-knowledge-space-theory/#python
